fastapi_simple_rbac/__init__.py
fastapi_simple_rbac/decorators.py
fastapi_simple_rbac/exceptions.py
fastapi_simple_rbac/middleware.py
fastapi_simple_rbac/types.py
fastapi_simple_rbac/utils.py
fastapi_simple_rbac-0.1.1.dist-info/licenses/LICENSE
fastapi_simple_rbac-0.1.1.dist-info/METADATA
fastapi_simple_rbac-0.1.1.dist-info/WHEEL
fastapi_simple_rbac-0.1.1.dist-info/top_level.txt
fastapi_simple_rbac-0.1.1.dist-info/RECORD
