Metadata-Version: 2.4
Name: fastapi-simple-rbac
Version: 0.1.1
Summary: Dead simple role-based access control for FastAPI
Author-email: Farid Darabi <farid.darabi@gmail.com>
License: MIT
Project-URL: Homepage, https://github.com/fariddarabi/fastapi-simple-rbac
Project-URL: Repository, https://github.com/faridarabi/fastapi-simple-rbac
Project-URL: Issues, https://github.com/fariddarabi/fastapi-simple-rbac/issues
Keywords: fastapi,rbac,auth,roles,permissions
Classifier: Development Status :: 4 - Beta
Classifier: Intended Audience :: Developers
Classifier: License :: OSI Approved :: MIT License
Classifier: Operating System :: OS Independent
Classifier: Programming Language :: Python :: 3
Classifier: Programming Language :: Python :: 3.8
Classifier: Programming Language :: Python :: 3.9
Classifier: Programming Language :: Python :: 3.10
Classifier: Programming Language :: Python :: 3.11
Classifier: Programming Language :: Python :: 3.12
Classifier: Framework :: FastAPI
Classifier: Topic :: Internet :: WWW/HTTP
Classifier: Topic :: Security
Requires-Python: >=3.8
License-File: LICENSE
Requires-Dist: fastapi>=0.68.0
Requires-Dist: python-jose[cryptography]>=3.3.0
Provides-Extra: dev
Requires-Dist: pytest>=7.0.0; extra == "dev"
Requires-Dist: pytest-asyncio>=0.21.0; extra == "dev"
Requires-Dist: pytest-cov>=4.0.0; extra == "dev"
Requires-Dist: httpx>=0.24.0; extra == "dev"
Requires-Dist: black>=22.0.0; extra == "dev"
Requires-Dist: isort>=5.10.0; extra == "dev"
Requires-Dist: flake8>=4.0.0; extra == "dev"
Requires-Dist: mypy>=0.991; extra == "dev"
Dynamic: license-file
